DirectAdminAPI_SGS_shohani/__init__.py
DirectAdminAPI_SGS_shohani/api.py
directadminapi_sgs_shohani-0.0.7.dist-info/METADATA
directadminapi_sgs_shohani-0.0.7.dist-info/WHEEL
directadminapi_sgs_shohani-0.0.7.dist-info/licenses/LICENSE
directadminapi_sgs_shohani-0.0.7.dist-info/RECORD
