Metadata-Version: 2.1
Name: DirectAdminAPI_SGS_shohani
Version: 0.0.7
Summary: DirectAdmin API for Python
Project-URL: Homepage, https://github.com/sadeghtkd/DirectAdminAPI_SGS
Project-URL: Bug Tracker, https://github.com/sadeghtkd/DirectAdminAPI_SGS/issues
Author-email: Sadegh Ghanbari Shohani <sadegh.tkd@gmail.com>
License-File: LICENSE
Classifier: License :: OSI Approved :: MIT License
Classifier: Operating System :: OS Independent
Classifier: Programming Language :: Python :: 3
Requires-Python: >=3.7
